MANIFEST.in
setup.py
meme_maker/__init__.py
meme_maker/__main__.py
meme_maker/cli.py
meme_maker/meme.py
meme_maker.egg-info/PKG-INFO
meme_maker.egg-info/SOURCES.txt
meme_maker.egg-info/dependency_links.txt
meme_maker.egg-info/entry_points.txt
meme_maker.egg-info/requires.txt
meme_maker.egg-info/top_level.txt
meme_maker/assets/impact.ttf
meme_maker/tests/__init__.py
meme_maker/tests/test_meme.py
requirements/base.txt
requirements/dev.txt
requirements/prod.txt
requirements/serverless.txt
requirements/test.txt