Metadata-Version: 1.1
Name: meme-maker
Version: 0.6
Summary: CLI, API and Slack bot to generate memes. Make memes not war.
Home-page: https://github.com/jacekszubert/meme-maker
Author: Jacek Szubert
Author-email: jacek.szubert@gmail.com
License: MIT
Keywords: meme,memes,slack,bot,api,cli,generator
Platform: UNKNOWN
Classifier: Intended Audience :: Developers
Classifier: License :: OSI Approved :: BSD License
Classifier: Programming Language :: Python
Classifier: Topic :: Software Development :: Libraries :: Python Modules
